tenable_sc_config/__init__.py
tenable_sc_config/config.py
tenable_sc_config/errors.py
tenable_sc_config-1.0.3.dist-info/LICENSE.txt
tenable_sc_config-1.0.3.dist-info/METADATA
tenable_sc_config-1.0.3.dist-info/WHEEL
tenable_sc_config-1.0.3.dist-info/top_level.txt
tenable_sc_config-1.0.3.dist-info/RECORD
