Metadata-Version: 2.1
Name: tenable-sc-config
Version: 1.0.3
Summary: A simple tool to create & load an .ini file for logging into an instance of Tenable.SC
Home-page: https://github.com/umanther/tenable_sc_config
Author: Geoff Hellstrand
Author-email: ubil@hotmail.com
License: GPLv3
Keywords: python,tenable,security,center,SC,login,configuration,ini
Platform: UNKNOWN
Classifier: Programming Language :: Python :: 3
Classifier: License :: OSI Approved :: GNU General Public License v3 or later (GPLv3+)
Classifier: Operating System :: OS Independent
Classifier: Natural Language :: English
Classifier: Topic :: Utilities
Requires-Python: >=3.6
Requires-Dist: configparser (>=4.0.2)
